pyarc2/__init__.py
pyarc2/_types.py
pyarc2/py.typed
pyarc2/pyarc2.cpython-311-x86_64-linux-gnu.so
pyarc2/pyarc2.pyi
pyarc2.libs/libbeastlink-1-8ab1612b.0.so
pyarc2.libs/libblkid-a9167753.so.1.1.0
pyarc2.libs/libmount-ec61bd71.so.1.1.0
pyarc2.libs/libpcre2-8-516f4c9d.so.0.7.1
pyarc2.libs/libselinux-d0805dcb.so.1
pyarc2.libs/libudev-9eca6271.so.1.6.11
pyarc2.libs/libusb-1-1b307d35.0.so.0.2.0
pyarc2.libs/libuuid-95b83d40.so.1.3.0
pyarc2-0.6.0.dist-info/METADATA
pyarc2-0.6.0.dist-info/WHEEL
pyarc2-0.6.0.dist-info/RECORD
pyarc2-0.6.0.dist-info/licenses/LICENSE
