Metadata-Version: 2.4
Name: pyarc2
Version: 0.6.0
Classifier: Development Status :: 3 - Alpha
Classifier: Intended Audience :: Science/Research
Classifier: License :: OSI Approved :: Mozilla Public License 2.0 (MPL 2.0)
Classifier: Operating System :: Microsoft :: Windows :: Windows 8
Classifier: Operating System :: Microsoft :: Windows :: Windows 8.1
Classifier: Operating System :: Microsoft :: Windows :: Windows 10
Classifier: Operating System :: POSIX :: Linux
Classifier: Programming Language :: Python :: 3.10
Classifier: Programming Language :: Python :: 3.11
Classifier: Programming Language :: Python :: 3.12
Classifier: Programming Language :: Python :: 3.13
Classifier: Programming Language :: Rust
Classifier: Topic :: Scientific/Engineering
Classifier: Topic :: Software Development :: Libraries :: Python Modules
Requires-Dist: numpy>=1.18
License-File: LICENSE
Summary: High level Python bindings for the libarc2 library
Home-Page: http://arc-instruments.co.uk
Author: Spyros Stathopoulos <spyros@arc-instruments.co.uk>
Author-email: spyros@arc-instruments.co.uk
License: MPL-2.0
Requires-Python: >=3.10
Project-URL: Source Code, https://github.com/arc-instruments/pyarc2
